<?xml version='1.0' encoding='utf-8'?>
<annotation>
  <folder>20</folder>
  <filename>20210007513.jpg</filename>
  <path>D:\trash_dataset\20210007513.jpg</path>
  <source>
    <database>Unknown</database>
  </source>
  <size>
    <width>151</width>
    <height>298</height>
    <depth>3</depth>
  </size>
  <segmented>0</segmented>
  <object>
      <name>干电池</name>
      <pose>Unspecified</pose>
      <truncated>1</truncated>
      <difficult>0</difficult>
      <bndbox>
        <xmin>5</xmin>
        <ymin>29</ymin>
        <xmax>98</xmax>
        <ymax>250</ymax>
      </bndbox>
    </object>
    <object>
      <name>干电池</name>
      <pose>Unspecified</pose>
      <truncated>1</truncated>
      <difficult>0</difficult>
      <bndbox>
        <xmin>1</xmin>
        <ymin>1</ymin>
        <xmax>27</xmax>
        <ymax>164</ymax>
      </bndbox>
    </object>
  </annotation>