<?xml version='1.0' encoding='utf-8'?>
<annotation>
  <folder>鞋-王佳莹</folder>
  <filename>20210003707.jpg</filename>
  <path>D:\trash_dataset\20210003707.jpg</path>
  <source>
    <database>Unknown</database>
  </source>
  <size>
    <width>660</width>
    <height>660</height>
    <depth>3</depth>
  </size>
  <segmented>0</segmented>
  <object>
      <name>鞋</name>
      <pose>Unspecified</pose>
      <truncated>1</truncated>
      <difficult>0</difficult>
      <bndbox>
        <xmin>44</xmin>
        <ymin>168</ymin>
        <xmax>530</xmax>
        <ymax>659</ymax>
      </bndbox>
    </object>
  </annotation>