<?xml version='1.0' encoding='utf-8'?>
<annotation>
  <folder>调料瓶1-孙双艳</folder>
  <filename>20210005276.jpg</filename>
  <path>D:\trash_dataset\20210005276.jpg</path>
  <source>
    <database>Unknown</database>
  </source>
  <size>
    <width>484</width>
    <height>1024</height>
    <depth>3</depth>
  </size>
  <segmented>0</segmented>
  <object>
      <name>调料瓶</name>
      <pose>Unspecified</pose>
      <truncated>1</truncated>
      <difficult>0</difficult>
      <bndbox>
        <xmin>164</xmin>
        <ymin>77</ymin>
        <xmax>304</xmax>
        <ymax>672</ymax>
      </bndbox>
    </object>
    <object>
      <name>金属厨具</name>
      <pose>Unspecified</pose>
      <truncated>1</truncated>
      <difficult>0</difficult>
      <bndbox>
        <xmin>144</xmin>
        <ymin>47</ymin>
        <xmax>481</xmax>
        <ymax>394</ymax>
      </bndbox>
    </object>
  </annotation>