<?xml version='1.0' encoding='utf-8'?>
<annotation>
	<folder>果皮果肉</folder>
	<filename>20210009435.jpg</filename>
	<path>D:\trash_dataset\20210009435.jpg</path>
	<source>
		<database>Unknown</database>
	</source>
	<size>
		<width>385</width>
		<height>285</height>
		<depth>3</depth>
	</size>
	<segmented>0</segmented>
	<object>
		<name>果皮果肉</name>
		<pose>Unspecified</pose>
		<truncated>0</truncated>
		<difficult>0</difficult>
		<bndbox>
			<xmin>7</xmin>
			<ymin>31</ymin>
			<xmax>365</xmax>
			<ymax>253</ymax>
		</bndbox>
	</object>
</annotation>