<?xml version='1.0' encoding='utf-8'?>
<annotation>
  <folder>茶叶渣</folder>
  <filename>20210010680.jpg</filename>
  <path>D:\trash_dataset\20210010680.jpg</path>
  <source>
    <database>Unknown</database>
  </source>
  <size>
    <width>517</width>
    <height>450</height>
    <depth>3</depth>
  </size>
  <segmented>0</segmented>
  <object>
      <name>茶叶渣</name>
      <pose>Unspecified</pose>
      <truncated>1</truncated>
      <difficult>0</difficult>
      <bndbox>
        <xmin>95</xmin>
        <ymin>172</ymin>
        <xmax>405</xmax>
        <ymax>397</ymax>
      </bndbox>
    </object>
    <object>
      <name>陶瓷器皿</name>
      <pose>Unspecified</pose>
      <truncated>1</truncated>
      <difficult>0</difficult>
      <bndbox>
        <xmin>45</xmin>
        <ymin>128</ymin>
        <xmax>441</xmax>
        <ymax>419</ymax>
      </bndbox>
    </object>
  </annotation>