<?xml version='1.0' encoding='utf-8'?>
<annotation>
  <folder>13</folder>
  <filename>20210000428.jpg</filename>
  <path>D:\trash_dataset\20210000428.jpg</path>
  <source>
    <database>Unknown</database>
  </source>
  <size>
    <width>355</width>
    <height>295</height>
    <depth>3</depth>
  </size>
  <segmented>0</segmented>
  <object>
      <name>插头电线</name>
      <pose>Unspecified</pose>
      <truncated>1</truncated>
      <difficult>0</difficult>
      <bndbox>
        <xmin>170</xmin>
        <ymin>104</ymin>
        <xmax>323</xmax>
        <ymax>294</ymax>
      </bndbox>
    </object>
    <object>
      <name>插头电线</name>
      <pose>Unspecified</pose>
      <truncated>1</truncated>
      <difficult>0</difficult>
      <bndbox>
        <xmin>23</xmin>
        <ymin>0</ymin>
        <xmax>210</xmax>
        <ymax>275</ymax>
      </bndbox>
    </object>
  </annotation>