<?xml version='1.0' encoding='utf-8'?>
<annotation>
	<folder>干电池</folder>
	<filename>20210007180.jpg</filename>
	<path>D:\trash_dataset\20210007180.jpg</path>
	<source>
		<database>Unknown</database>
	</source>
	<size>
		<width>400</width>
		<height>256</height>
		<depth>3</depth>
	</size>
	<segmented>0</segmented>
	<object>
		<name>干电池</name>
		<pose>Unspecified</pose>
		<truncated>0</truncated>
		<difficult>0</difficult>
		<bndbox>
			<xmin>44</xmin>
			<ymin>59</ymin>
			<xmax>307</xmax>
			<ymax>166</ymax>
		</bndbox>
	</object>
</annotation>