<?xml version='1.0' encoding='utf-8'?>
<annotation>
  <folder>8</folder>
  <filename>20210012500.jpg</filename>
  <path>D:\trash_dataset\20210012500.jpg</path>
  <source>
    <database>Unknown</database>
  </source>
  <size>
    <width>750</width>
    <height>750</height>
    <depth>3</depth>
  </size>
  <segmented>0</segmented>
  <object>
      <name>充电宝</name>
      <pose>Unspecified</pose>
      <truncated>1</truncated>
      <difficult>0</difficult>
      <bndbox>
        <xmin>195</xmin>
        <ymin>8</ymin>
        <xmax>744</xmax>
        <ymax>702</ymax>
      </bndbox>
    </object>
    <object>
      <name>饮料瓶</name>
      <pose>Unspecified</pose>
      <truncated>1</truncated>
      <difficult>0</difficult>
      <bndbox>
        <xmin>51</xmin>
        <ymin>0</ymin>
        <xmax>246</xmax>
        <ymax>195</ymax>
      </bndbox>
    </object>
  </annotation>