<?xml version='1.0' encoding='utf-8'?>
<annotation>
  <folder>6</folder>
  <filename>20210008722.jpg</filename>
  <path>D:\trash_dataset\20210008722.jpg</path>
  <source>
    <database>Unknown</database>
  </source>
  <size>
    <width>1024</width>
    <height>682</height>
    <depth>3</depth>
  </size>
  <segmented>0</segmented>
  <object>
      <name>剩饭剩菜</name>
      <pose>Unspecified</pose>
      <truncated>1</truncated>
      <difficult>0</difficult>
      <bndbox>
        <xmin>108</xmin>
        <ymin>250</ymin>
        <xmax>734</xmax>
        <ymax>539</ymax>
      </bndbox>
    </object>
    <object>
      <name>剩饭剩菜</name>
      <pose>Unspecified</pose>
      <truncated>1</truncated>
      <difficult>0</difficult>
      <bndbox>
        <xmin>748</xmin>
        <ymin>296</ymin>
        <xmax>1023</xmax>
        <ymax>623</ymax>
      </bndbox>
    </object>
    <object>
      <name>剩饭剩菜</name>
      <pose>Unspecified</pose>
      <truncated>1</truncated>
      <difficult>0</difficult>
      <bndbox>
        <xmin>541</xmin>
        <ymin>94</ymin>
        <xmax>781</xmax>
        <ymax>282</ymax>
      </bndbox>
    </object>
    <object>
      <name>剩饭剩菜</name>
      <pose>Unspecified</pose>
      <truncated>1</truncated>
      <difficult>0</difficult>
      <bndbox>
        <xmin>103</xmin>
        <ymin>59</ymin>
        <xmax>524</xmax>
        <ymax>169</ymax>
      </bndbox>
    </object>
    <object>
      <name>陶瓷器皿</name>
      <pose>Unspecified</pose>
      <truncated>1</truncated>
      <difficult>0</difficult>
      <bndbox>
        <xmin>53</xmin>
        <ymin>167</ymin>
        <xmax>787</xmax>
        <ymax>674</ymax>
      </bndbox>
    </object>
    <object>
      <name>陶瓷器皿</name>
      <pose>Unspecified</pose>
      <truncated>1</truncated>
      <difficult>0</difficult>
      <bndbox>
        <xmin>61</xmin>
        <ymin>0</ymin>
        <xmax>567</xmax>
        <ymax>233</ymax>
      </bndbox>
    </object>
    <object>
      <name>玻璃器皿</name>
      <pose>Unspecified</pose>
      <truncated>1</truncated>
      <difficult>0</difficult>
      <bndbox>
        <xmin>890</xmin>
        <ymin>48</ymin>
        <xmax>1023</xmax>
        <ymax>403</ymax>
      </bndbox>
    </object>
    <object>
      <name>玻璃器皿</name>
      <pose>Unspecified</pose>
      <truncated>1</truncated>
      <difficult>0</difficult>
      <bndbox>
        <xmin>760</xmin>
        <ymin>1</ymin>
        <xmax>1023</xmax>
        <ymax>290</ymax>
      </bndbox>
    </object>
  </annotation>