<?xml version='1.0' encoding='utf-8'?>
<annotation>
  <folder>13</folder>
  <filename>20210000994.jpg</filename>
  <path>D:\trash_dataset\20210000994.jpg</path>
  <source>
    <database>Unknown</database>
  </source>
  <size>
    <width>399</width>
    <height>485</height>
    <depth>3</depth>
  </size>
  <segmented>0</segmented>
  <object>
      <name>插头电线</name>
      <pose>Unspecified</pose>
      <truncated>1</truncated>
      <difficult>0</difficult>
      <bndbox>
        <xmin>197</xmin>
        <ymin>171</ymin>
        <xmax>361</xmax>
        <ymax>264</ymax>
      </bndbox>
    </object>
    <object>
      <name>插头电线</name>
      <pose>Unspecified</pose>
      <truncated>1</truncated>
      <difficult>0</difficult>
      <bndbox>
        <xmin>80</xmin>
        <ymin>19</ymin>
        <xmax>190</xmax>
        <ymax>96</ymax>
      </bndbox>
    </object>
    <object>
      <name>插头电线</name>
      <pose>Unspecified</pose>
      <truncated>1</truncated>
      <difficult>0</difficult>
      <bndbox>
        <xmin>1</xmin>
        <ymin>110</ymin>
        <xmax>150</xmax>
        <ymax>183</ymax>
      </bndbox>
    </object>
  </annotation>