<?xml version='1.0' encoding='utf-8'?>
<annotation>
  <folder>砧板-孙双艳</folder>
  <filename>20210004250.jpg</filename>
  <path>D:\trash_dataset\20210004250.jpg</path>
  <source>
    <database>Unknown</database>
  </source>
  <size>
    <width>500</width>
    <height>375</height>
    <depth>3</depth>
  </size>
  <segmented>0</segmented>
  <object>
      <name>砧板</name>
      <pose>Unspecified</pose>
      <truncated>1</truncated>
      <difficult>0</difficult>
      <bndbox>
        <xmin>91</xmin>
        <ymin>82</ymin>
        <xmax>455</xmax>
        <ymax>353</ymax>
      </bndbox>
    </object>
    <object>
      <name>砧板</name>
      <pose>Unspecified</pose>
      <truncated>1</truncated>
      <difficult>0</difficult>
      <bndbox>
        <xmin>251</xmin>
        <ymin>1</ymin>
        <xmax>485</xmax>
        <ymax>143</ymax>
      </bndbox>
    </object>
    <object>
      <name>砧板</name>
      <pose>Unspecified</pose>
      <truncated>1</truncated>
      <difficult>0</difficult>
      <bndbox>
        <xmin>437</xmin>
        <ymin>3</ymin>
        <xmax>499</xmax>
        <ymax>93</ymax>
      </bndbox>
    </object>
  </annotation>